evaluation_service_base/__init__.py
evaluation_service_base/charts/__init__.py
evaluation_service_base/charts/dtypes.py
evaluation_service_base/core/__init__.py
evaluation_service_base/core/base_service.py
evaluation_service_base/core/common.py
evaluation_service_base/core/constants.py
evaluation_service_base/core/enum.py
evaluation_service_base/core/exceptions.py
evaluation_service_base/core/managers.py
evaluation_service_base/core/models.py
evaluation_service_base/core/reporters.py
evaluation_service_base/utils/__init__.py
evaluation_service_base/utils/minio_client.py
evaluation_service_base/utils/minio_url.py
evaluation_service_base/utils/s3_handler.py
evaluation_service_base-0.1.4.dist-info/LICENSE
evaluation_service_base-0.1.4.dist-info/METADATA
evaluation_service_base-0.1.4.dist-info/WHEEL
evaluation_service_base-0.1.4.dist-info/top_level.txt
evaluation_service_base-0.1.4.dist-info/RECORD
