Metadata-Version: 2.1
Name: evaluation-service-base
Version: 0.1.4
Summary: A comprehensive framework for building evaluation services with progress tracking, task management, and result handling
Author-email: yx <wuyixuan1111@gmail.com>
Maintainer-email: yx <wuyixuan1111@gmail.com>
License: MIT
Project-URL: Homepage, https://github.com/yx-1111101/evaluation-service
Project-URL: Repository, https://github.com/yx-1111101/evaluation-service.git
Project-URL: Bug Tracker, https://github.com/yx-1111101/evaluation-service/issues
Project-URL: Documentation, https://evaluation-service.readthedocs.io/
Project-URL: Changelog, https://github.com/yx-1111101/evaluation-service/blob/main/CHANGELOG.md
Keywords: evaluation,service,framework,progress-tracking,task-management,s3,minio,charts,visualization,ai,machine-learning,data-processing
Classifier: Development Status :: 4 - Beta
Classifier: Intended Audience :: Developers
Classifier: Intended Audience :: Science/Research
Classifier: Topic :: Software Development :: Libraries :: Python Modules
Classifier: Topic :: Scientific/Engineering :: Artificial Intelligence
Classifier: Topic :: System :: Monitoring
Classifier: License :: OSI Approved :: MIT License
Classifier: Operating System :: OS Independent
Classifier: Programming Language :: Python :: 3
Classifier: Programming Language :: Python :: 3.8
Classifier: Programming Language :: Python :: 3.9
Classifier: Programming Language :: Python :: 3.10
Classifier: Programming Language :: Python :: 3.11
Classifier: Programming Language :: Python :: 3.12
Classifier: Programming Language :: Python :: 3 :: Only
Classifier: Typing :: Typed
Requires-Python: >=3.8
License-File: LICENSE
Requires-Dist: pydantic>=2.0.0
Requires-Dist: pandas>=1.3.0
Requires-Dist: minio>=7.0.0
Requires-Dist: h5py>=3.0.0
Requires-Dist: liblogging
Requires-Dist: libentry
Requires-Dist: tables==3.10.2
Provides-Extra: dev
Requires-Dist: pytest>=7.0.0; extra == "dev"
Requires-Dist: pytest-cov>=4.0.0; extra == "dev"
Requires-Dist: pytest-mock>=3.10.0; extra == "dev"
Requires-Dist: black>=23.0.0; extra == "dev"
Requires-Dist: flake8>=6.0.0; extra == "dev"
Requires-Dist: isort>=5.12.0; extra == "dev"
Requires-Dist: mypy>=1.0.0; extra == "dev"
Requires-Dist: pre-commit>=3.0.0; extra == "dev"
Provides-Extra: docs
Requires-Dist: sphinx>=5.0.0; extra == "docs"
Requires-Dist: sphinx-rtd-theme>=1.2.0; extra == "docs"
Requires-Dist: myst-parser>=0.18.0; extra == "docs"
Requires-Dist: sphinx-autodoc-typehints>=1.19.0; extra == "docs"
Provides-Extra: test
Requires-Dist: pytest>=7.0.0; extra == "test"
Requires-Dist: pytest-cov>=4.0.0; extra == "test"
Requires-Dist: pytest-mock>=3.10.0; extra == "test"
Requires-Dist: pytest-asyncio>=0.21.0; extra == "test"
